tests
guildwars2api
