Metadata-Version: 1.1
Name: guildwars2api
Version: 0.7.1
Summary: A Python API Wrapper for the Guild Wars 2 API
Home-page: https://github.com/menglewis/guildwars2api
Author: David Lewis
Author-email: meng.lewis@gmail.com
License: BSD
Keywords: guildwars2api
Platform: UNKNOWN
Classifier: Development Status :: 2 - Pre-Alpha
Classifier: Intended Audience :: Developers
Classifier: License :: OSI Approved :: BSD License
Classifier: Natural Language :: English
Classifier: Programming Language :: Python :: 2
Classifier: Programming Language :: Python :: 2.6
Classifier: Programming Language :: Python :: 2.7
Classifier: Programming Language :: Python :: 3
Classifier: Programming Language :: Python :: 3.3
Classifier: Programming Language :: Python :: 3.4
